[
  {
    "id": 190,
    "name": "Clint Eastwood",
    "popularity": 28.008,
    "cast_id": 4,
    "order": 0,
    "character": "William Munny",
    "credit_id": "52fe4211c3a36847f8001447"
  },
  {
    "id": 193,
    "name": "Gene Hackman",
    "popularity": 18.488,
    "cast_id": 6,
    "order": 1,
    "character": "'Little' Bill Daggett",
    "credit_id": "52fe4211c3a36847f800144b"
  },
  {
    "id": 192,
    "name": "Morgan Freeman",
    "popularity": 42.867,
    "cast_id": 25,
    "order": 2,
    "character": "Ned Logan",
    "credit_id": "52fe4211c3a36847f80014a5"
  },
  {
    "id": 194,
    "name": "Richard Harris",
    "popularity": 13.259,
    "cast_id": 7,
    "order": 3,
    "character": "English Bob",
    "credit_id": "52fe4211c3a36847f800144f"
  },
  {
    "id": 3710,
    "name": "Jaimz Woolvett",
    "popularity": 5.997,
    "cast_id": 9,
    "order": 4,
    "character": "The Schofield Kid",
    "credit_id": "52fe4211c3a36847f8001459"
  },
  {
    "id": 3711,
    "name": "Anna Levine Thomson",
    "popularity": 11.112,
    "cast_id": 10,
    "order": 5,
    "character": "Delilah Fitzgerald",
    "credit_id": "52fe4211c3a36847f800145d"
  },
  {
    "id": 3712,
    "name": "Saul Rubinek",
    "popularity": 8.103,
    "cast_id": 11,
    "order": 6,
    "character": "W.W. Beauchamp",
    "credit_id": "52fe4211c3a36847f8001461"
  },
  {
    "id": 3713,
    "name": "Frances Fisher",
    "popularity": 59.534,
    "cast_id": 12,
    "order": 7,
    "character": "Strawberry Alice",
    "credit_id": "52fe4211c3a36847f8001465"
  },
  {
    "id": 3714,
    "name": "David Mucci",
    "popularity": 2.531,
    "cast_id": 13,
    "order": 8,
    "character": "Quick Mike",
    "credit_id": "52fe4211c3a36847f8001469"
  },
  {
    "id": 2843,
    "name": "Rob Campbell",
    "popularity": 3.176,
    "cast_id": 14,
    "order": 9,
    "character": "Davey Bunting",
    "credit_id": "52fe4211c3a36847f800146d"
  },
  {
    "id": 3715,
    "name": "Anthony James",
    "popularity": 4.699,
    "cast_id": 15,
    "order": 10,
    "character": "Skinny Dubois",
    "credit_id": "52fe4211c3a36847f8001471"
  },
  {
    "id": 1242148,
    "name": "Ron White",
    "popularity": 3.342,
    "cast_id": 28,
    "order": 11,
    "character": "Clyde Ledbetter",
    "credit_id": "5468f5b4eaeb816b4f001312"
  },
  {
    "id": 185111,
    "name": "Jefferson Mappin",
    "popularity": 3.159,
    "cast_id": 29,
    "order": 12,
    "character": "Fatty Rossiter",
    "credit_id": "56610e9b925141791800584d"
  },
  {
    "id": 44205,
    "name": "Jeremy Ratchford",
    "popularity": 8.185,
    "cast_id": 30,
    "order": 13,
    "character": "Deputy Andy Russell",
    "credit_id": "56610ed5c3a36875e2005ce9"
  },
  {
    "id": 976171,
    "name": "Philip Maurice Hayes",
    "popularity": 3.623,
    "cast_id": 31,
    "order": 14,
    "character": "Lippy MacGregor",
    "credit_id": "56e5cec2c3a36807b2000f48"
  },
  {
    "id": 58058,
    "name": "Lochlyn Munro",
    "popularity": 20.129,
    "cast_id": 43,
    "order": 26,
    "character": "Texas Slim",
    "credit_id": "56f813979251410a310006fb"
  }
]