[
  {
    "id": 1158,
    "name": "Al Pacino",
    "popularity": 40.622,
    "cast_id": 12,
    "order": 0,
    "character": "Lowell Bergman",
    "credit_id": "52fe44d1c3a36847f80abae3"
  },
  {
    "id": 934,
    "name": "Russell Crowe",
    "popularity": 38.607,
    "cast_id": 13,
    "order": 1,
    "character": "Jeffrey Wigand",
    "credit_id": "52fe44d1c3a36847f80abae7"
  },
  {
    "id": 290,
    "name": "Christopher Plummer",
    "popularity": 7.841,
    "cast_id": 14,
    "order": 2,
    "character": "Mike Wallace",
    "credit_id": "52fe44d1c3a36847f80abaeb"
  },
  {
    "id": 6200,
    "name": "Diane Venora",
    "popularity": 13.099,
    "cast_id": 15,
    "order": 3,
    "character": "Liane Wigand",
    "credit_id": "52fe44d1c3a36847f80abaef"
  },
  {
    "id": 4492,
    "name": "Philip Baker Hall",
    "popularity": 7.195,
    "cast_id": 16,
    "order": 4,
    "character": "Don Hewitt",
    "credit_id": "52fe44d1c3a36847f80abaf3"
  },
  {
    "id": 32225,
    "name": "Lindsay Crouse",
    "popularity": 7.729,
    "cast_id": 17,
    "order": 5,
    "character": "Sharon Tiller",
    "credit_id": "52fe44d1c3a36847f80abaf7"
  },
  {
    "id": 5578,
    "name": "Debi Mazar",
    "popularity": 8.294,
    "cast_id": 18,
    "order": 6,
    "character": "Debbie De Luca",
    "credit_id": "52fe44d1c3a36847f80abafb"
  },
  {
    "id": 537,
    "name": "Stephen Tobolowsky",
    "popularity": 11.333,
    "cast_id": 19,
    "order": 7,
    "character": "Eric Kluster",
    "credit_id": "52fe44d1c3a36847f80abaff"
  },
  {
    "id": 10132,
    "name": "Colm Feore",
    "popularity": 11.758,
    "cast_id": 20,
    "order": 8,
    "character": "Richard Scruggs",
    "credit_id": "52fe44d1c3a36847f80abb03"
  },
  {
    "id": 14888,
    "name": "Bruce McGill",
    "popularity": 15.722,
    "cast_id": 21,
    "order": 9,
    "character": "Ron Motley",
    "credit_id": "52fe44d1c3a36847f80abb07"
  },
  {
    "id": 11150,
    "name": "Gina Gershon",
    "popularity": 23.45,
    "cast_id": 22,
    "order": 10,
    "character": "Helen Caperelli",
    "credit_id": "52fe44d1c3a36847f80abb0b"
  },
  {
    "id": 5658,
    "name": "Michael Gambon",
    "popularity": 21.281,
    "cast_id": 23,
    "order": 11,
    "character": "Thomas Sandefur",
    "credit_id": "52fe44d1c3a36847f80abb0f"
  },
  {
    "id": 9626,
    "name": "Rip Torn",
    "popularity": 13.393,
    "cast_id": 24,
    "order": 12,
    "character": "John Scanlon",
    "credit_id": "52fe44d1c3a36847f80abb13"
  },
  {
    "id": 61153,
    "name": "Wings Hauser",
    "popularity": 14.666,
    "cast_id": 32,
    "order": 20,
    "character": "Tobacco Lawyer",
    "credit_id": "52fe44d1c3a36847f80abb33"
  },
  {
    "id": 7248,
    "name": "Cliff Curtis",
    "popularity": 15.447,
    "cast_id": 33,
    "order": 21,
    "character": "Sheikh Fadlallah",
    "credit_id": "52fe44d1c3a36847f80abb37"
  },
  {
    "id": 57991,
    "name": "Wanda De Jesus",
    "popularity": 11.129,
    "cast_id": 74,
    "order": 38,
    "character": "Geologist / FBI Woman",
    "credit_id": "56d0860f9251416e3a003a0b"
  },
  {
    "id": 33654,
    "name": "Breckin Meyer",
    "popularity": 14.55,
    "cast_id": 79,
    "order": 43,
    "character": "Sharon's Son",
    "credit_id": "56d086f9c3a3681e3c00717b"
  }
]